btctrade/__init__.py
btctrade-0.1.7.dist-info/METADATA
btctrade-0.1.7.dist-info/WHEEL
btctrade-0.1.7.dist-info/top_level.txt
btctrade-0.1.7.dist-info/RECORD
