Metadata-Version: 2.1
Name: btctrade
Version: 0.1.7
Summary: Api for site btc-trade.com.ua/
Home-page: http://github.com/FerumFlex/btctrade
Author: FerumFlex
Author-email: ferumflex@gmail.com
License: MIT
Platform: UNKNOWN
Classifier: Intended Audience :: Developers
Classifier: Intended Audience :: System Administrators
Classifier: Operating System :: OS Independent
Classifier: Topic :: Software Development
Classifier: Programming Language :: Python :: 3
Classifier: Programming Language :: Python :: 3.4
Classifier: Programming Language :: Python :: 3.5
Classifier: Programming Language :: Python :: 3.6
Requires-Dist: requests
